{
	"meta": {
		"chronografVersion": "1.7.10",
		"sources": {
			"0": {
				"name": "http://192.168.9.11:8086",
				"link": "/chronograf/v1/sources/0"
			}
		}
	},
	"dashboard": {
		"id": 55,
		"cells": [
			{
				"i": "d3a85e6b-893f-4a76-b798-c9546061ed17",
				"x": 6,
				"y": 0,
				"w": 2,
				"h": 3,
				"name": "Power - :host: - :gpu:",
				"queries": [
					{
						"query": "SELECT last(\"power_draw\") FROM \"telegraf\"..\"nvidia_smi\" WHERE time > :dashboardTime: AND \"host\"=':host:' AND \"uuid\"=':gpu:'",
						"queryConfig": {
							"database": "telegraf",
							"measurement": "nvidia_smi",
							"retentionPolicy": "",
							"fields": [
								{
									"value": "last",
									"type": "func",
									"alias": "",
									"args": [
										{
											"value": "power_draw",
											"type": "field",
											"alias": ""
										}
									]
								}
							],
							"tags": {
								"host": [
									":host:"
								],
								"uuid": [
									":gpu:"
								]
							},
							"groupBy": {
								"time": "",
								"tags": []
							},
							"areTagsAccepted": true,
							"rawText": null,
							"range": null,
							"shifts": null
						},
						"source": "",
						"type": "influxql"
					}
				],
				"axes": {
					"x": {
						"bounds": [
							"",
							""
						],
						"label": "",
						"prefix": "",
						"suffix": "",
						"base": "10",
						"scale": "linear"
					},
					"y": {
						"bounds": [
							"0",
							""
						],
						"label": "utilization",
						"prefix": "",
						"suffix": "W",
						"base": "raw",
						"scale": "linear"
					},
					"y2": {
						"bounds": [
							"",
							""
						],
						"label": "",
						"prefix": "",
						"suffix": "",
						"base": "10",
						"scale": "linear"
					}
				},
				"type": "gauge",
				"colors": [
					{
						"id": "0",
						"type": "min",
						"hex": "#32B08C",
						"name": "viridian",
						"value": "0"
					},
					{
						"id": "1",
						"type": "max",
						"hex": "#DC4E58",
						"name": "fire",
						"value": "200"
					}
				],
				"legend": {},
				"tableOptions": {
					"verticalTimeAxis": true,
					"sortBy": {
						"internalName": "time",
						"displayName": "",
						"visible": true
					},
					"wrapping": "truncate",
					"fixFirstColumn": true
				},
				"fieldOptions": [
					{
						"internalName": "time",
						"displayName": "",
						"visible": true
					}
				],
				"timeFormat": "MM/DD/YYYY HH:mm:ss",
				"decimalPlaces": {
					"isEnforced": true,
					"digits": 1
				},
				"note": "",
				"noteVisibility": "default",
				"links": {
					"self": "/chronograf/v1/dashboards/55/cells/d3a85e6b-893f-4a76-b798-c9546061ed17"
				}
			},
			{
				"i": "718335f9-691a-476d-9441-194a9b2c7f2f",
				"x": 8,
				"y": 0,
				"w": 2,
				"h": 3,
				"name": "Temperature - :host: - :gpu:",
				"queries": [
					{
						"query": "SELECT last(\"temperature_gpu\") FROM \"telegraf\"..\"nvidia_smi\" WHERE time > :dashboardTime: AND \"host\"=':host:' AND \"uuid\"=':gpu:'",
						"queryConfig": {
							"database": "telegraf",
							"measurement": "nvidia_smi",
							"retentionPolicy": "",
							"fields": [
								{
									"value": "last",
									"type": "func",
									"alias": "",
									"args": [
										{
											"value": "temperature_gpu",
											"type": "field",
											"alias": ""
										}
									]
								}
							],
							"tags": {
								"host": [
									":host:"
								],
								"uuid": [
									":gpu:"
								]
							},
							"groupBy": {
								"time": "",
								"tags": []
							},
							"areTagsAccepted": true,
							"rawText": null,
							"range": null,
							"shifts": null
						},
						"source": "",
						"type": "influxql"
					}
				],
				"axes": {
					"x": {
						"bounds": [
							"",
							""
						],
						"label": "",
						"prefix": "",
						"suffix": "",
						"base": "10",
						"scale": "linear"
					},
					"y": {
						"bounds": [
							"0",
							""
						],
						"label": "utilization",
						"prefix": "",
						"suffix": " C",
						"base": "raw",
						"scale": "linear"
					},
					"y2": {
						"bounds": [
							"",
							""
						],
						"label": "",
						"prefix": "",
						"suffix": "",
						"base": "10",
						"scale": "linear"
					}
				},
				"type": "gauge",
				"colors": [
					{
						"id": "0",
						"type": "min",
						"hex": "#00C9FF",
						"name": "laser",
						"value": "30"
					},
					{
						"id": "1",
						"type": "max",
						"hex": "#DC4E58",
						"name": "fire",
						"value": "100"
					}
				],
				"legend": {},
				"tableOptions": {
					"verticalTimeAxis": true,
					"sortBy": {
						"internalName": "time",
						"displayName": "",
						"visible": true
					},
					"wrapping": "truncate",
					"fixFirstColumn": true
				},
				"fieldOptions": [
					{
						"internalName": "time",
						"displayName": "",
						"visible": true
					}
				],
				"timeFormat": "MM/DD/YYYY HH:mm:ss",
				"decimalPlaces": {
					"isEnforced": true,
					"digits": 1
				},
				"note": "",
				"noteVisibility": "default",
				"links": {
					"self": "/chronograf/v1/dashboards/55/cells/718335f9-691a-476d-9441-194a9b2c7f2f"
				}
			},
			{
				"i": "e72d24c5-56b7-4ee4-9a52-125e05a73b47",
				"x": 0,
				"y": 2,
				"w": 2,
				"h": 1,
				"name": "Memory Size - :host: - :gpu:",
				"queries": [
					{
						"query": "SELECT mean(\"memory_total\") FROM \"telegraf\"..\"nvidia_smi\" WHERE time > :dashboardTime: AND \"host\"=':host:' AND \"uuid\"=':gpu:'",
						"queryConfig": {
							"database": "telegraf",
							"measurement": "nvidia_smi",
							"retentionPolicy": "",
							"fields": [
								{
									"value": "mean",
									"type": "func",
									"alias": "",
									"args": [
										{
											"value": "memory_total",
											"type": "field",
											"alias": ""
										}
									]
								}
							],
							"tags": {
								"host": [
									":host:"
								],
								"uuid": [
									":gpu:"
								]
							},
							"groupBy": {
								"time": "",
								"tags": []
							},
							"areTagsAccepted": true,
							"rawText": null,
							"range": null,
							"shifts": null
						},
						"source": "",
						"type": "influxql"
					}
				],
				"axes": {
					"x": {
						"bounds": [
							"",
							""
						],
						"label": "",
						"prefix": "",
						"suffix": "",
						"base": "10",
						"scale": "linear"
					},
					"y": {
						"bounds": [
							"0",
							""
						],
						"label": "megabytes",
						"prefix": "",
						"suffix": " MB",
						"base": "raw",
						"scale": "linear"
					},
					"y2": {
						"bounds": [
							"",
							""
						],
						"label": "",
						"prefix": "",
						"suffix": "",
						"base": "10",
						"scale": "linear"
					}
				},
				"type": "single-stat",
				"colors": [
					{
						"id": "base",
						"type": "text",
						"hex": "#00C9FF",
						"name": "laser",
						"value": "-1000000000000000000"
					}
				],
				"legend": {},
				"tableOptions": {
					"verticalTimeAxis": true,
					"sortBy": {
						"internalName": "time",
						"displayName": "",
						"visible": true
					},
					"wrapping": "truncate",
					"fixFirstColumn": true
				},
				"fieldOptions": [
					{
						"internalName": "time",
						"displayName": "",
						"visible": true
					}
				],
				"timeFormat": "MM/DD/YYYY HH:mm:ss",
				"decimalPlaces": {
					"isEnforced": true,
					"digits": 2
				},
				"note": "",
				"noteVisibility": "default",
				"links": {
					"self": "/chronograf/v1/dashboards/55/cells/e72d24c5-56b7-4ee4-9a52-125e05a73b47"
				}
			},
			{
				"i": "17eae793-ae7b-4fcc-810b-fe7c58a780ca",
				"x": 10,
				"y": 0,
				"w": 2,
				"h": 3,
				"name": "Fan Speed - :host: - :gpu:",
				"queries": [
					{
						"query": "SELECT last(\"fan_speed\") FROM \"telegraf\"..\"nvidia_smi\" WHERE time > :dashboardTime: AND \"host\"=':host:' AND \"uuid\"=':gpu:'",
						"queryConfig": {
							"database": "telegraf",
							"measurement": "nvidia_smi",
							"retentionPolicy": "",
							"fields": [
								{
									"value": "last",
									"type": "func",
									"alias": "",
									"args": [
										{
											"value": "fan_speed",
											"type": "field",
											"alias": ""
										}
									]
								}
							],
							"tags": {
								"host": [
									":host:"
								],
								"uuid": [
									":gpu:"
								]
							},
							"groupBy": {
								"time": "",
								"tags": []
							},
							"areTagsAccepted": true,
							"rawText": null,
							"range": null,
							"shifts": null
						},
						"source": "",
						"type": "influxql"
					}
				],
				"axes": {
					"x": {
						"bounds": [
							"",
							""
						],
						"label": "",
						"prefix": "",
						"suffix": "",
						"base": "10",
						"scale": "linear"
					},
					"y": {
						"bounds": [
							"0",
							""
						],
						"label": "utilization",
						"prefix": "",
						"suffix": "%",
						"base": "raw",
						"scale": "linear"
					},
					"y2": {
						"bounds": [
							"",
							""
						],
						"label": "",
						"prefix": "",
						"suffix": "",
						"base": "10",
						"scale": "linear"
					}
				},
				"type": "gauge",
				"colors": [
					{
						"id": "0",
						"type": "min",
						"hex": "#32B08C",
						"name": "viridian",
						"value": "0"
					},
					{
						"id": "1",
						"type": "max",
						"hex": "#DC4E58",
						"name": "fire",
						"value": "100"
					}
				],
				"legend": {},
				"tableOptions": {
					"verticalTimeAxis": true,
					"sortBy": {
						"internalName": "time",
						"displayName": "",
						"visible": true
					},
					"wrapping": "truncate",
					"fixFirstColumn": true
				},
				"fieldOptions": [
					{
						"internalName": "time",
						"displayName": "",
						"visible": true
					}
				],
				"timeFormat": "MM/DD/YYYY HH:mm:ss",
				"decimalPlaces": {
					"isEnforced": true,
					"digits": 2
				},
				"note": "",
				"noteVisibility": "default",
				"links": {
					"self": "/chronograf/v1/dashboards/55/cells/17eae793-ae7b-4fcc-810b-fe7c58a780ca"
				}
			},
			{
				"i": "64783149-979a-41c6-88c6-d7c702c67599",
				"x": 4,
				"y": 0,
				"w": 2,
				"h": 3,
				"name": "Memory Utilization - :host: - :gpu:",
				"queries": [
					{
						"query": "SELECT last(\"utilization_memory\") FROM \"telegraf\"..\"nvidia_smi\" WHERE time > :dashboardTime: AND \"host\"=':host:' AND \"uuid\"=':gpu:'",
						"queryConfig": {
							"database": "telegraf",
							"measurement": "nvidia_smi",
							"retentionPolicy": "",
							"fields": [
								{
									"value": "last",
									"type": "func",
									"alias": "",
									"args": [
										{
											"value": "utilization_memory",
											"type": "field",
											"alias": ""
										}
									]
								}
							],
							"tags": {
								"host": [
									":host:"
								],
								"uuid": [
									":gpu:"
								]
							},
							"groupBy": {
								"time": "",
								"tags": []
							},
							"areTagsAccepted": true,
							"rawText": null,
							"range": null,
							"shifts": null
						},
						"source": "",
						"type": "influxql"
					}
				],
				"axes": {
					"x": {
						"bounds": [
							"",
							""
						],
						"label": "",
						"prefix": "",
						"suffix": "",
						"base": "10",
						"scale": "linear"
					},
					"y": {
						"bounds": [
							"0",
							""
						],
						"label": "utilization",
						"prefix": "",
						"suffix": "%",
						"base": "raw",
						"scale": "linear"
					},
					"y2": {
						"bounds": [
							"",
							""
						],
						"label": "",
						"prefix": "",
						"suffix": "",
						"base": "10",
						"scale": "linear"
					}
				},
				"type": "gauge",
				"colors": [
					{
						"id": "0",
						"type": "min",
						"hex": "#32B08C",
						"name": "viridian",
						"value": "0"
					},
					{
						"id": "1",
						"type": "max",
						"hex": "#DC4E58",
						"name": "fire",
						"value": "100"
					}
				],
				"legend": {},
				"tableOptions": {
					"verticalTimeAxis": true,
					"sortBy": {
						"internalName": "time",
						"displayName": "",
						"visible": true
					},
					"wrapping": "truncate",
					"fixFirstColumn": true
				},
				"fieldOptions": [
					{
						"internalName": "time",
						"displayName": "",
						"visible": true
					}
				],
				"timeFormat": "MM/DD/YYYY HH:mm:ss",
				"decimalPlaces": {
					"isEnforced": true,
					"digits": 2
				},
				"note": "",
				"noteVisibility": "default",
				"links": {
					"self": "/chronograf/v1/dashboards/55/cells/64783149-979a-41c6-88c6-d7c702c67599"
				}
			},
			{
				"i": "0f3a8fe7-0881-421c-9dd3-b7a045bdf492",
				"x": 2,
				"y": 0,
				"w": 2,
				"h": 3,
				"name": "GPU Utilization - :host: - :gpu:",
				"queries": [
					{
						"query": "SELECT last(\"utilization_gpu\") FROM \"telegraf\"..\"nvidia_smi\" WHERE time > :dashboardTime: AND \"host\"=':host:' AND \"uuid\"=':gpu:'",
						"queryConfig": {
							"database": "telegraf",
							"measurement": "nvidia_smi",
							"retentionPolicy": "",
							"fields": [
								{
									"value": "last",
									"type": "func",
									"alias": "",
									"args": [
										{
											"value": "utilization_gpu",
											"type": "field",
											"alias": ""
										}
									]
								}
							],
							"tags": {
								"host": [
									":host:"
								],
								"uuid": [
									":gpu:"
								]
							},
							"groupBy": {
								"time": "",
								"tags": []
							},
							"areTagsAccepted": true,
							"rawText": null,
							"range": null,
							"shifts": null
						},
						"source": "",
						"type": "influxql"
					}
				],
				"axes": {
					"x": {
						"bounds": [
							"",
							""
						],
						"label": "",
						"prefix": "",
						"suffix": "",
						"base": "10",
						"scale": "linear"
					},
					"y": {
						"bounds": [
							"0",
							""
						],
						"label": "utilization",
						"prefix": "",
						"suffix": "%",
						"base": "raw",
						"scale": "linear"
					},
					"y2": {
						"bounds": [
							"",
							""
						],
						"label": "",
						"prefix": "",
						"suffix": "",
						"base": "10",
						"scale": "linear"
					}
				},
				"type": "gauge",
				"colors": [
					{
						"id": "0",
						"type": "min",
						"hex": "#32B08C",
						"name": "viridian",
						"value": "0"
					},
					{
						"id": "1",
						"type": "max",
						"hex": "#DC4E58",
						"name": "fire",
						"value": "100"
					}
				],
				"legend": {},
				"tableOptions": {
					"verticalTimeAxis": true,
					"sortBy": {
						"internalName": "time",
						"displayName": "",
						"visible": true
					},
					"wrapping": "truncate",
					"fixFirstColumn": true
				},
				"fieldOptions": [
					{
						"internalName": "time",
						"displayName": "",
						"visible": true
					}
				],
				"timeFormat": "MM/DD/YYYY HH:mm:ss",
				"decimalPlaces": {
					"isEnforced": true,
					"digits": 2
				},
				"note": "",
				"noteVisibility": "default",
				"links": {
					"self": "/chronograf/v1/dashboards/55/cells/0f3a8fe7-0881-421c-9dd3-b7a045bdf492"
				}
			},
			{
				"i": "fb30ffd2-8800-4207-a426-35559bdff39a",
				"x": 0,
				"y": 0,
				"w": 2,
				"h": 2,
				"name": "GPU Name - :host: - :gpu:",
				"queries": [
					{
						"query": "SHOW TAG VALUES ON \"telegraf\" FROM \"nvidia_smi\" WITH KEY=\"name\" WHERE \"host\"=':host:' AND \"uuid\"=':gpu:'",
						"queryConfig": {
							"database": "",
							"measurement": "",
							"retentionPolicy": "",
							"fields": [],
							"tags": {},
							"groupBy": {
								"time": "",
								"tags": []
							},
							"areTagsAccepted": false,
							"rawText": "SHOW TAG VALUES ON \"telegraf\" FROM \"nvidia_smi\" WITH KEY=\"name\" WHERE \"host\"=':host:' AND \"uuid\"=':gpu:'",
							"range": null,
							"shifts": null
						},
						"source": "",
						"type": "influxql"
					}
				],
				"axes": {
					"x": {
						"bounds": [
							"",
							""
						],
						"label": "",
						"prefix": "",
						"suffix": "",
						"base": "10",
						"scale": "linear"
					},
					"y": {
						"bounds": [
							"0",
							""
						],
						"label": "utilization",
						"prefix": "",
						"suffix": "",
						"base": "raw",
						"scale": "linear"
					},
					"y2": {
						"bounds": [
							"",
							""
						],
						"label": "",
						"prefix": "",
						"suffix": "",
						"base": "10",
						"scale": "linear"
					}
				},
				"type": "table",
				"colors": [
					{
						"id": "base",
						"type": "text",
						"hex": "#00C9FF",
						"name": "laser",
						"value": "-1000000000000000000"
					}
				],
				"legend": {},
				"tableOptions": {
					"verticalTimeAxis": true,
					"sortBy": {
						"internalName": "time",
						"displayName": "",
						"visible": true
					},
					"wrapping": "truncate",
					"fixFirstColumn": true
				},
				"fieldOptions": [
					{
						"internalName": "value",
						"displayName": "",
						"visible": true
					},
					{
						"internalName": "key",
						"displayName": "",
						"visible": true
					}
				],
				"timeFormat": "MM/DD/YYYY HH:mm:ss",
				"decimalPlaces": {
					"isEnforced": true,
					"digits": 0
				},
				"note": "",
				"noteVisibility": "default",
				"links": {
					"self": "/chronograf/v1/dashboards/55/cells/fb30ffd2-8800-4207-a426-35559bdff39a"
				}
			},
			{
				"i": "c948fc9b-471c-4152-a93e-72f1d3263ed3",
				"x": 0,
				"y": 9,
				"w": 6,
				"h": 3,
				"name": "Memory Used - :host: - :gpu:",
				"queries": [
					{
						"query": "SELECT mean(\"memory_used\") AS \"memory used\" FROM \"telegraf\"..\"nvidia_smi\" WHERE time > :dashboardTime: AND \"host\"=':host:' AND \"uuid\"=':gpu:' GROUP BY time(:interval:) FILL(null)",
						"queryConfig": {
							"database": "telegraf",
							"measurement": "nvidia_smi",
							"retentionPolicy": "",
							"fields": [
								{
									"value": "mean",
									"type": "func",
									"alias": "memory used",
									"args": [
										{
											"value": "memory_used",
											"type": "field",
											"alias": ""
										}
									]
								}
							],
							"tags": {
								"host": [
									":host:"
								],
								"uuid": [
									":gpu:"
								]
							},
							"groupBy": {
								"time": "auto",
								"tags": []
							},
							"areTagsAccepted": true,
							"fill": "null",
							"rawText": null,
							"range": null,
							"shifts": null
						},
						"source": "",
						"type": "influxql"
					}
				],
				"axes": {
					"x": {
						"bounds": [
							"",
							""
						],
						"label": "",
						"prefix": "",
						"suffix": "",
						"base": "10",
						"scale": "linear"
					},
					"y": {
						"bounds": [
							"0",
							""
						],
						"label": "megabytes",
						"prefix": "",
						"suffix": " MB",
						"base": "raw",
						"scale": "linear"
					},
					"y2": {
						"bounds": [
							"",
							""
						],
						"label": "",
						"prefix": "",
						"suffix": "",
						"base": "10",
						"scale": "linear"
					}
				},
				"type": "line",
				"colors": [
					{
						"id": "75749e8b-b791-4f85-9c68-ec8b462150ce",
						"type": "scale",
						"hex": "#31C0F6",
						"name": "Nineteen Eighty Four",
						"value": "0"
					},
					{
						"id": "087be227-8635-4e40-aad4-76da54a33b96",
						"type": "scale",
						"hex": "#A500A5",
						"name": "Nineteen Eighty Four",
						"value": "0"
					},
					{
						"id": "5515b8ca-ec41-4156-b50f-b7268e5c672a",
						"type": "scale",
						"hex": "#FF7E27",
						"name": "Nineteen Eighty Four",
						"value": "0"
					}
				],
				"legend": {},
				"tableOptions": {
					"verticalTimeAxis": true,
					"sortBy": {
						"internalName": "time",
						"displayName": "",
						"visible": true
					},
					"wrapping": "truncate",
					"fixFirstColumn": true
				},
				"fieldOptions": [
					{
						"internalName": "time",
						"displayName": "",
						"visible": true
					}
				],
				"timeFormat": "MM/DD/YYYY HH:mm:ss",
				"decimalPlaces": {
					"isEnforced": true,
					"digits": 2
				},
				"note": "",
				"noteVisibility": "default",
				"links": {
					"self": "/chronograf/v1/dashboards/55/cells/c948fc9b-471c-4152-a93e-72f1d3263ed3"
				}
			},
			{
				"i": "01c8c2ca-c704-47fe-a357-dcbeb0061643",
				"x": 0,
				"y": 6,
				"w": 6,
				"h": 3,
				"name": "Memory Utilization - :host: - :gpu:",
				"queries": [
					{
						"query": "SELECT mean(\"utilization_memory\") AS \"memory utilization\" FROM \"telegraf\"..\"nvidia_smi\" WHERE time > :dashboardTime: AND \"host\"=':host:' AND \"uuid\"=':gpu:' GROUP BY time(:interval:) FILL(null)",
						"queryConfig": {
							"database": "telegraf",
							"measurement": "nvidia_smi",
							"retentionPolicy": "",
							"fields": [
								{
									"value": "mean",
									"type": "func",
									"alias": "memory utilization",
									"args": [
										{
											"value": "utilization_memory",
											"type": "field",
											"alias": ""
										}
									]
								}
							],
							"tags": {
								"host": [
									":host:"
								],
								"uuid": [
									":gpu:"
								]
							},
							"groupBy": {
								"time": "auto",
								"tags": []
							},
							"areTagsAccepted": true,
							"fill": "null",
							"rawText": null,
							"range": null,
							"shifts": null
						},
						"source": "",
						"type": "influxql"
					}
				],
				"axes": {
					"x": {
						"bounds": [
							"",
							""
						],
						"label": "",
						"prefix": "",
						"suffix": "",
						"base": "10",
						"scale": "linear"
					},
					"y": {
						"bounds": [
							"0",
							""
						],
						"label": "utilization",
						"prefix": "",
						"suffix": "%",
						"base": "raw",
						"scale": "linear"
					},
					"y2": {
						"bounds": [
							"",
							""
						],
						"label": "",
						"prefix": "",
						"suffix": "",
						"base": "10",
						"scale": "linear"
					}
				},
				"type": "line",
				"colors": [
					{
						"id": "75749e8b-b791-4f85-9c68-ec8b462150ce",
						"type": "scale",
						"hex": "#31C0F6",
						"name": "Nineteen Eighty Four",
						"value": "0"
					},
					{
						"id": "087be227-8635-4e40-aad4-76da54a33b96",
						"type": "scale",
						"hex": "#A500A5",
						"name": "Nineteen Eighty Four",
						"value": "0"
					},
					{
						"id": "5515b8ca-ec41-4156-b50f-b7268e5c672a",
						"type": "scale",
						"hex": "#FF7E27",
						"name": "Nineteen Eighty Four",
						"value": "0"
					}
				],
				"legend": {},
				"tableOptions": {
					"verticalTimeAxis": true,
					"sortBy": {
						"internalName": "time",
						"displayName": "",
						"visible": true
					},
					"wrapping": "truncate",
					"fixFirstColumn": true
				},
				"fieldOptions": [
					{
						"internalName": "time",
						"displayName": "",
						"visible": true
					}
				],
				"timeFormat": "MM/DD/YYYY HH:mm:ss",
				"decimalPlaces": {
					"isEnforced": true,
					"digits": 2
				},
				"note": "",
				"noteVisibility": "default",
				"links": {
					"self": "/chronograf/v1/dashboards/55/cells/01c8c2ca-c704-47fe-a357-dcbeb0061643"
				}
			},
			{
				"i": "6a9096a3-e1f1-4195-9a09-9e23ee0551cb",
				"x": 6,
				"y": 6,
				"w": 6,
				"h": 3,
				"name": "Temperature - :host: - :gpu: (clone 1)",
				"queries": [
					{
						"query": "SELECT mean(\"temperature_gpu\") AS \"GPU temperature\" FROM \"telegraf\"..\"nvidia_smi\" WHERE time > :dashboardTime: AND \"host\"=':host:' AND \"uuid\"=':gpu:' GROUP BY time(:interval:) FILL(null)",
						"queryConfig": {
							"database": "telegraf",
							"measurement": "nvidia_smi",
							"retentionPolicy": "",
							"fields": [
								{
									"value": "mean",
									"type": "func",
									"alias": "GPU temperature",
									"args": [
										{
											"value": "temperature_gpu",
											"type": "field",
											"alias": ""
										}
									]
								}
							],
							"tags": {
								"host": [
									":host:"
								],
								"uuid": [
									":gpu:"
								]
							},
							"groupBy": {
								"time": "auto",
								"tags": []
							},
							"areTagsAccepted": true,
							"fill": "null",
							"rawText": null,
							"range": null,
							"shifts": null
						},
						"source": "",
						"type": "influxql"
					}
				],
				"axes": {
					"x": {
						"bounds": [
							"",
							""
						],
						"label": "",
						"prefix": "",
						"suffix": "",
						"base": "10",
						"scale": "linear"
					},
					"y": {
						"bounds": [
							"0",
							""
						],
						"label": "temperature",
						"prefix": "",
						"suffix": "C",
						"base": "raw",
						"scale": "linear"
					},
					"y2": {
						"bounds": [
							"",
							""
						],
						"label": "",
						"prefix": "",
						"suffix": "",
						"base": "10",
						"scale": "linear"
					}
				},
				"type": "line",
				"colors": [
					{
						"id": "75749e8b-b791-4f85-9c68-ec8b462150ce",
						"type": "scale",
						"hex": "#31C0F6",
						"name": "Nineteen Eighty Four",
						"value": "0"
					},
					{
						"id": "087be227-8635-4e40-aad4-76da54a33b96",
						"type": "scale",
						"hex": "#A500A5",
						"name": "Nineteen Eighty Four",
						"value": "0"
					},
					{
						"id": "5515b8ca-ec41-4156-b50f-b7268e5c672a",
						"type": "scale",
						"hex": "#FF7E27",
						"name": "Nineteen Eighty Four",
						"value": "0"
					}
				],
				"legend": {},
				"tableOptions": {
					"verticalTimeAxis": true,
					"sortBy": {
						"internalName": "time",
						"displayName": "",
						"visible": true
					},
					"wrapping": "truncate",
					"fixFirstColumn": true
				},
				"fieldOptions": [
					{
						"internalName": "time",
						"displayName": "",
						"visible": true
					}
				],
				"timeFormat": "MM/DD/YYYY HH:mm:ss",
				"decimalPlaces": {
					"isEnforced": true,
					"digits": 2
				},
				"note": "",
				"noteVisibility": "default",
				"links": {
					"self": "/chronograf/v1/dashboards/55/cells/6a9096a3-e1f1-4195-9a09-9e23ee0551cb"
				}
			},
			{
				"i": "858b4257-6cb6-415a-a0c4-4980ba6b14e5",
				"x": 0,
				"y": 3,
				"w": 6,
				"h": 3,
				"name": "GPU Utilization - :host: - :gpu:",
				"queries": [
					{
						"query": "SELECT mean(\"utilization_gpu\") AS \"GPU utilization\" FROM \"telegraf\"..\"nvidia_smi\" WHERE time > :dashboardTime: AND \"host\"=':host:' AND \"uuid\"=':gpu:' GROUP BY time(:interval:) FILL(null)",
						"queryConfig": {
							"database": "telegraf",
							"measurement": "nvidia_smi",
							"retentionPolicy": "",
							"fields": [
								{
									"value": "mean",
									"type": "func",
									"alias": "GPU utilization",
									"args": [
										{
											"value": "utilization_gpu",
											"type": "field",
											"alias": ""
										}
									]
								}
							],
							"tags": {
								"host": [
									":host:"
								],
								"uuid": [
									":gpu:"
								]
							},
							"groupBy": {
								"time": "auto",
								"tags": []
							},
							"areTagsAccepted": true,
							"fill": "null",
							"rawText": null,
							"range": null,
							"shifts": null
						},
						"source": "",
						"type": "influxql"
					}
				],
				"axes": {
					"x": {
						"bounds": [
							"",
							""
						],
						"label": "",
						"prefix": "",
						"suffix": "",
						"base": "10",
						"scale": "linear"
					},
					"y": {
						"bounds": [
							"0",
							""
						],
						"label": "utilization",
						"prefix": "",
						"suffix": "%",
						"base": "raw",
						"scale": "linear"
					},
					"y2": {
						"bounds": [
							"",
							""
						],
						"label": "",
						"prefix": "",
						"suffix": "",
						"base": "10",
						"scale": "linear"
					}
				},
				"type": "line",
				"colors": [
					{
						"id": "75749e8b-b791-4f85-9c68-ec8b462150ce",
						"type": "scale",
						"hex": "#31C0F6",
						"name": "Nineteen Eighty Four",
						"value": "0"
					},
					{
						"id": "087be227-8635-4e40-aad4-76da54a33b96",
						"type": "scale",
						"hex": "#A500A5",
						"name": "Nineteen Eighty Four",
						"value": "0"
					},
					{
						"id": "5515b8ca-ec41-4156-b50f-b7268e5c672a",
						"type": "scale",
						"hex": "#FF7E27",
						"name": "Nineteen Eighty Four",
						"value": "0"
					}
				],
				"legend": {},
				"tableOptions": {
					"verticalTimeAxis": true,
					"sortBy": {
						"internalName": "time",
						"displayName": "",
						"visible": true
					},
					"wrapping": "truncate",
					"fixFirstColumn": true
				},
				"fieldOptions": [
					{
						"internalName": "time",
						"displayName": "",
						"visible": true
					}
				],
				"timeFormat": "MM/DD/YYYY HH:mm:ss",
				"decimalPlaces": {
					"isEnforced": true,
					"digits": 2
				},
				"note": "",
				"noteVisibility": "default",
				"links": {
					"self": "/chronograf/v1/dashboards/55/cells/858b4257-6cb6-415a-a0c4-4980ba6b14e5"
				}
			},
			{
				"i": "19d269fd-56e9-4892-9b83-53425d4f12d2",
				"x": 6,
				"y": 3,
				"w": 6,
				"h": 3,
				"name": "Power Draw - :host: - :gpu:",
				"queries": [
					{
						"query": "SELECT max(\"power_draw\") AS \"power draw\" FROM \"telegraf\"..\"nvidia_smi\" WHERE time > :dashboardTime: AND \"host\"=':host:' AND \"uuid\"=':gpu:' GROUP BY time(:interval:) FILL(null)",
						"queryConfig": {
							"database": "telegraf",
							"measurement": "nvidia_smi",
							"retentionPolicy": "",
							"fields": [
								{
									"value": "max",
									"type": "func",
									"alias": "power draw",
									"args": [
										{
											"value": "power_draw",
											"type": "field",
											"alias": ""
										}
									]
								}
							],
							"tags": {
								"host": [
									":host:"
								],
								"uuid": [
									":gpu:"
								]
							},
							"groupBy": {
								"time": "auto",
								"tags": []
							},
							"areTagsAccepted": true,
							"fill": "null",
							"rawText": null,
							"range": null,
							"shifts": null
						},
						"source": "",
						"type": "influxql"
					}
				],
				"axes": {
					"x": {
						"bounds": [
							"",
							""
						],
						"label": "",
						"prefix": "",
						"suffix": "",
						"base": "10",
						"scale": "linear"
					},
					"y": {
						"bounds": [
							"0",
							""
						],
						"label": "power",
						"prefix": "",
						"suffix": "W",
						"base": "raw",
						"scale": "linear"
					},
					"y2": {
						"bounds": [
							"",
							""
						],
						"label": "",
						"prefix": "",
						"suffix": "",
						"base": "10",
						"scale": "linear"
					}
				},
				"type": "line",
				"colors": [
					{
						"id": "75749e8b-b791-4f85-9c68-ec8b462150ce",
						"type": "scale",
						"hex": "#31C0F6",
						"name": "Nineteen Eighty Four",
						"value": "0"
					},
					{
						"id": "087be227-8635-4e40-aad4-76da54a33b96",
						"type": "scale",
						"hex": "#A500A5",
						"name": "Nineteen Eighty Four",
						"value": "0"
					},
					{
						"id": "5515b8ca-ec41-4156-b50f-b7268e5c672a",
						"type": "scale",
						"hex": "#FF7E27",
						"name": "Nineteen Eighty Four",
						"value": "0"
					}
				],
				"legend": {},
				"tableOptions": {
					"verticalTimeAxis": true,
					"sortBy": {
						"internalName": "time",
						"displayName": "",
						"visible": true
					},
					"wrapping": "truncate",
					"fixFirstColumn": true
				},
				"fieldOptions": [
					{
						"internalName": "time",
						"displayName": "",
						"visible": true
					}
				],
				"timeFormat": "MM/DD/YYYY HH:mm:ss",
				"decimalPlaces": {
					"isEnforced": true,
					"digits": 2
				},
				"note": "",
				"noteVisibility": "default",
				"links": {
					"self": "/chronograf/v1/dashboards/55/cells/19d269fd-56e9-4892-9b83-53425d4f12d2"
				}
			},
			{
				"i": "39a02e20-a820-4961-964f-9b5c35a96cd7",
				"x": 6,
				"y": 9,
				"w": 6,
				"h": 3,
				"name": "Fan Speed - :host: - :gpu:",
				"queries": [
					{
						"query": "SELECT mean(\"fan_speed\") AS \"fan speed\" FROM \"telegraf\"..\"nvidia_smi\" WHERE time > :dashboardTime: AND \"host\"=':host:' AND \"uuid\"=':gpu:' GROUP BY time(:interval:) FILL(null)",
						"queryConfig": {
							"database": "telegraf",
							"measurement": "nvidia_smi",
							"retentionPolicy": "",
							"fields": [
								{
									"value": "mean",
									"type": "func",
									"alias": "fan speed",
									"args": [
										{
											"value": "fan_speed",
											"type": "field",
											"alias": ""
										}
									]
								}
							],
							"tags": {
								"host": [
									":host:"
								],
								"uuid": [
									":gpu:"
								]
							},
							"groupBy": {
								"time": "auto",
								"tags": []
							},
							"areTagsAccepted": true,
							"fill": "null",
							"rawText": null,
							"range": null,
							"shifts": null
						},
						"source": "",
						"type": "influxql"
					}
				],
				"axes": {
					"x": {
						"bounds": [
							"",
							""
						],
						"label": "",
						"prefix": "",
						"suffix": "",
						"base": "10",
						"scale": "linear"
					},
					"y": {
						"bounds": [
							"0",
							""
						],
						"label": "fan speed",
						"prefix": "",
						"suffix": "%",
						"base": "raw",
						"scale": "linear"
					},
					"y2": {
						"bounds": [
							"",
							""
						],
						"label": "",
						"prefix": "",
						"suffix": "",
						"base": "10",
						"scale": "linear"
					}
				},
				"type": "line",
				"colors": [
					{
						"id": "75749e8b-b791-4f85-9c68-ec8b462150ce",
						"type": "scale",
						"hex": "#31C0F6",
						"name": "Nineteen Eighty Four",
						"value": "0"
					},
					{
						"id": "087be227-8635-4e40-aad4-76da54a33b96",
						"type": "scale",
						"hex": "#A500A5",
						"name": "Nineteen Eighty Four",
						"value": "0"
					},
					{
						"id": "5515b8ca-ec41-4156-b50f-b7268e5c672a",
						"type": "scale",
						"hex": "#FF7E27",
						"name": "Nineteen Eighty Four",
						"value": "0"
					}
				],
				"legend": {},
				"tableOptions": {
					"verticalTimeAxis": true,
					"sortBy": {
						"internalName": "time",
						"displayName": "",
						"visible": true
					},
					"wrapping": "truncate",
					"fixFirstColumn": true
				},
				"fieldOptions": [
					{
						"internalName": "time",
						"displayName": "",
						"visible": true
					}
				],
				"timeFormat": "MM/DD/YYYY HH:mm:ss",
				"decimalPlaces": {
					"isEnforced": true,
					"digits": 2
				},
				"note": "",
				"noteVisibility": "default",
				"links": {
					"self": "/chronograf/v1/dashboards/55/cells/39a02e20-a820-4961-964f-9b5c35a96cd7"
				}
			}
		],
		"templates": [
			{
				"tempVar": ":host:",
				"values": [
					{
						"value": "knode1",
						"type": "influxql",
						"selected": true
					}
				],
				"id": "09f94aa0-ff13-436a-a700-3a484ea03edf",
				"type": "influxql",
				"label": "",
				"query": {
					"influxql": "SHOW TAG VALUES ON \"telegraf\" FROM \"nvidia_smi\" WITH KEY=\"host\"",
					"measurement": "",
					"tagKey": "",
					"fieldKey": ""
				},
				"links": {
					"self": "/chronograf/v1/dashboards/55/templates/09f94aa0-ff13-436a-a700-3a484ea03edf"
				}
			},
			{
				"tempVar": ":gpu:",
				"values": [
					{
						"value": "GPU-9a8bc0f1-3c5f-bfe8-fd9b-b24bd460faa9",
						"type": "influxql",
						"selected": true
					}
				],
				"id": "ea28fe34-c108-4a1b-b059-b997bb1ca5a0",
				"type": "influxql",
				"label": "",
				"query": {
					"influxql": "SHOW TAG VALUES ON \"telegraf\" FROM \"nvidia_smi\" WITH KEY=\"uuid\" WHERE \"host\"=':host:'",
					"measurement": "",
					"tagKey": "",
					"fieldKey": ""
				},
				"links": {
					"self": "/chronograf/v1/dashboards/55/templates/ea28fe34-c108-4a1b-b059-b997bb1ca5a0"
				}
			}
		],
		"name": "NVIDIA: GPU Performance",
		"organization": "default",
		"links": {
			"self": "/chronograf/v1/dashboards/55",
			"cells": "/chronograf/v1/dashboards/55/cells",
			"templates": "/chronograf/v1/dashboards/55/templates"
		}
	}
}